{
  "data": [
    {
      "id": "1",
      "name": "Ikswobel Golf",
      "url": "https://www.youtube.com/watch?v=30DBupP9Go8",
      "description": "Connects golfers to other golfers",
      "languages": [
        {
          "name": "Ruby on Rails",
          "iconifyClass": "logos-ruby"
        },
        {
          "name": "React",
          "iconifyClass": "logos-react"
        },
        {
          "name": "NPM",
          "iconifyClass": "logos-npm"
        }
      ]
    },
    {
      "id": "2",
      "name": "Vibez",
      "url": "https://github.com/PhilipRoush/mod_2_project",
      "description": "Music playlist creating App.",
      "languages": [
        {
          "name": "Ruby on Rails",
          "iconifyClass": "logos-ruby"
        }
      ]
    },
    {
      "id": "12",
      "name": "World of Movies",
      "url": "https://github.com/PhilipRoush/mod-4-project",
      "description": "Netflix like movie app. Search movies and get descriptions and poster.",
      "languages": [
        {
          "name": "Ruby on Rails",
          "iconifyClass": "logos-ruby"
        },
        {
          "name": "ReactJS",
          "iconifyClass": "logos-react"
        },
        {
          "name": "NPM",
          "iconifyClass": "logos-npm"
        }
      ]
    }
    
  ]
}
